agibot_videodataset.libs/libavcodec-0512960a.so.61.19.101
agibot_videodataset.libs/libavformat-c0299cb6.so.61.7.100
agibot_videodataset.libs/libavutil-699a117a.so.59.39.100
agibot_videodataset.libs/libswresample-d2c5b480.so.5.3.100
videodataset/__init__.py
videodataset/_decoder.cpython-314-aarch64-linux-gnu.so
videodataset/_decoder.pyi
videodataset/py.typed
videodataset/dataset/__init__.py
videodataset/dataset/base_dataset.py
agibot_videodataset-0.1.5.dist-info/METADATA
agibot_videodataset-0.1.5.dist-info/WHEEL
agibot_videodataset-0.1.5.dist-info/RECORD
agibot_videodataset-0.1.5.dist-info/licenses/LICENSE
