Metadata-Version: 2.1
Name: agibot-videodataset
Version: 0.1.5
Summary: A GPU-accelerated library that enables random frame access and efficient video decoding for data loading.
Keywords: dataset,nvcodec,serious-scaffold,video
Author-Email: genie <genie@agibot.com>
License: MIT
Classifier: Development Status :: 3 - Alpha
Classifier: Intended Audience :: Developers
Classifier: Intended Audience :: Science/Research
Classifier: License :: OSI Approved :: MIT License
Classifier: Operating System :: POSIX :: Linux
Classifier: Programming Language :: Python :: 3 :: Only
Classifier: Programming Language :: Python :: 3.10
Classifier: Programming Language :: Python :: 3.11
Classifier: Programming Language :: Python :: 3.12
Classifier: Programming Language :: Python :: 3.13
Classifier: Programming Language :: Python :: 3.14
Classifier: Topic :: Scientific/Engineering
Classifier: Typing :: Typed
Project-URL: documentation, https://AgiBot-World.github.io/VideoDataset
Project-URL: issue, https://github.com/AgiBot-World/VideoDataset/issues
Project-URL: repository, https://github.com/AgiBot-World/VideoDataset
Requires-Python: >=3.10
Requires-Dist: numpy
Requires-Dist: torch>=2.2.1
